{
  "main": {
    "id": "4a0788d70f90f4de",
    "type": "split",
    "children": [
      {
        "id": "7e3fe4c9fda138fd",
        "type": "tabs",
        "children": [
          {
            "id": "a2e2729b08c6a0f1",
            "type": "leaf",
            "pinned": true,
            "state": {
              "type": "graph",
              "state": {},
              "pinned": true
            }
          },
          {
            "id": "a50330d265f39a5e",
            "type": "leaf",
            "state": {
              "type": "markdown",
              "state": {
                "file": "01 后端/01 Java/01 通用语法/Variable.md",
                "mode": "source",
                "backlinks": false,
                "source": false
              }
            }
          },
          {
            "id": "bd85c5a5729e1e32",
            "type": "leaf",
            "state": {
              "type": "markdown",
              "state": {
                "file": "01 后端/01 Java/03 常用类/Tableaux.md",
                "mode": "source",
                "backlinks": false,
                "source": false
              }
            }
          }
        ],
        "currentTab": 1
      }
    ],
    "direction": "vertical"
  },
  "left": {
    "id": "da184a9c4d6721bf",
    "type": "split",
    "children": [
      {
        "id": "899c39b9e8b05f3c",
        "type": "tabs",
        "children": [
          {
            "id": "de25684b297de1b0",
            "type": "leaf",
            "state": {
              "type": "search",
              "state": {
                "query": "tag:#stream",
                "matchingCase": false,
                "explainSearch": false,
                "collapseAll": false,
                "extraContext": false,
                "sortOrder": "alphabetical"
              }
            }
          },
          {
            "id": "458439cc2f0a2fea",
            "type": "leaf",
            "state": {
              "type": "bookmarks",
              "state": {}
            }
          },
          {
            "id": "30ad5320b3f66082",
            "type": "leaf",
            "state": {
              "type": "file-explorer",
              "state": {
                "sortOrder": "alphabetical"
              }
            }
          }
        ],
        "currentTab": 2
      }
    ],
    "direction": "horizontal",
    "width": 322.5
  },
  "right": {
    "id": "ef5f3f3cfbd40054",
    "type": "split",
    "children": [
      {
        "id": "2bbe0a8ab3625de1",
        "type": "tabs",
        "children": [
          {
            "id": "f3c3386f218d6c07",
            "type": "leaf",
            "state": {
              "type": "git-view",
              "state": {}
            }
          },
          {
            "id": "5a4b0a275414e989",
            "type": "leaf",
            "state": {
              "type": "outline",
              "state": {
                "file": "01 后端/01 Java/01 通用语法/Variable.md"
              }
            }
          },
          {
            "id": "9f366a752848195b",
            "type": "leaf",
            "state": {
              "type": "backlink",
              "state": {
                "file": "01 后端/01 Java/01 通用语法/Variable.md",
                "collapseAll": true,
                "extraContext": false,
                "sortOrder": "alphabetical",
                "showSearch": false,
                "searchQuery": "",
                "backlinkCollapsed": false,
                "unlinkedCollapsed": true
              }
            }
          },
          {
            "id": "2875d2462d5097a0",
            "type": "leaf",
            "state": {
              "type": "outgoing-link",
              "state": {
                "file": "01 后端/01 Java/01 通用语法/Variable.md",
                "linksCollapsed": false,
                "unlinkedCollapsed": true
              }
            }
          },
          {
            "id": "475d252b9dd1daff",
            "type": "leaf",
            "state": {
              "type": "tag",
              "state": {
                "sortOrder": "alphabetical",
                "useHierarchy": true
              }
            }
          }
        ]
      },
      {
        "id": "efc0cb6b19e319bf",
        "type": "tabs",
        "children": [
          {
            "id": "bf68c1627da9e263",
            "type": "leaf",
            "state": {
              "type": "advanced-tables-toolbar",
              "state": {}
            }
          },
          {
            "id": "c9b14f9950c4d7f2",
            "type": "leaf",
            "state": {
              "type": "side-panel-control-view",
              "state": {}
            }
          }
        ],
        "currentTab": 1
      }
    ],
    "direction": "horizontal",
    "width": 312.5
  },
  "left-ribbon": {
    "hiddenItems": {
      "graph:Ouvrir la vue graphique": false,
      "switcher:Ouvrir le sélecteur rapide": false,
      "templates:Insérer le modèle": false,
      "command-palette:Ouvrir la palette de commandes": false,
      "obsidian-file-cleaner:Clean files": false,
      "obsidian-markdown-formatting-assistant-plugin:Open Markdown Formatting Assistant": true,
      "table-editor-obsidian:Advanced Tables Toolbar": true,
      "obsidian-excalidraw-plugin:Create new drawing": false,
      "canvas:Créer une nouvelle toile": false
    }
  },
  "active": "f3c3386f218d6c07",
  "lastOpenFiles": [
    "01 后端/01 Java/03 常用类/Tableaux.md",
    "01 后端/01 Java/01 通用语法/Variable.md",
    "01 后端/01 Java/02 面向对象/Classe.md",
    "01 后端/01 Java/03 常用类/Type primitif.md",
    "Type élémentaire",
    "Sans titre.canvas",
    "01 后端/01 Java/03 常用类/字符串/String.md",
    "03 数据结构与算法/Kadane's Algorithm.md",
    "01 后端/01 Java/03 常用类/集合/Map/HashMap.md",
    "01 后端/01 Java/03 常用类/集合/Collection/List/List.md",
    "01 后端/01 Java/Quiz/Questions ouvertes.md",
    "01 后端/01 Java/04 进阶/Stream/Stream.md",
    "01 后端/01 Java/03 常用类/集合/Collection/Set/Set.md",
    "01 后端/01 Java/03 常用类/集合/Map/Map.md",
    "01 后端/01 Java/03 常用类/集合/Collection/Collection.md",
    "01 后端/01 Java/03 常用类/集合/Collection/Set/HashSet.md",
    "01 后端/01 Java/02 面向对象/Programmation orientée objet.md",
    "01 后端/01 Java/02 面向对象/Méthode.md",
    "01 后端/01 Java/04 进阶/Multi-thread.md",
    "Template/Collection Complexity.md",
    "01 后端/01 Java/03 常用类/集合/Collections.md",
    "01 后端/01 Java/01 通用语法/Hello Java.md",
    "01 后端/01 Java/02 面向对象/Module.md",
    "01 后端/01 Java/02 面向对象/Objet.md",
    "01 后端/01 Java/04 进阶/Stream/Functional interface.md",
    "01 后端/01 Java/03 常用类/集合/Map/LinkedHashMap.md",
    "面试/面试.md",
    "面试/Crédit Agricole.md",
    "Attachment/Pasted image 20230808122537.png",
    "images",
    "Attachment/Pasted image 20230803163811.png",
    "Attachment/Pasted image 20230803163620.png",
    "Attachment/Pasted image 20230223225441.png",
    "Excalidraw",
    "Attachment/Pasted image 20230720170411.png",
    "04 模式与思想",
    "03 数据结构与算法",
    "01 后端/04 框架/03 Spring Framework/Spring/AOP",
    "01 后端/04 框架/03 Spring Framework/Spring/Bean",
    "01 后端/04 框架/03 Spring Framework/SpringBoot",
    "01 后端/04 框架/03 Spring Framework/Spring",
    "01 后端/04 框架/02 Mybatis/进阶",
    "Attachment/Pasted image 20230712152402.png",
    "Attachment/Pasted image 20230622161652.png",
    "Attachment/Pasted image 20230105002447.png",
    "Attachment/Pasted image 20230618224915.png",
    "Attachment/Pasted image 20230419214403.png"
  ]
}